[
  {
    "user": {
      "type": "player",
      "name": "Manzarli",
      "uniqueId": "741f774b-754a-49eb-93ac-fa7c0c120c28"
    },
    "time": 1751366389065,
    "type": "Profiler",
    "data": {
      "type": "url",
      "value": "https://spark.lucko.me/hqD36BLLnK"
    }
  },
  {
    "user": {
      "type": "player",
      "name": "Manzarli",
      "uniqueId": "741f774b-754a-49eb-93ac-fa7c0c120c28"
    },
    "time": 1751126611255,
    "type": "Profiler",
    "data": {
      "type": "url",
      "value": "https://spark.lucko.me/fr4muoSIrf"
    }
  },
  {
    "user": {
      "type": "player",
      "name": "Manzarli",
      "uniqueId": "741f774b-754a-49eb-93ac-fa7c0c120c28"
    },
    "time": 1751106962958,
    "type": "Profiler",
    "data": {
      "type": "url",
      "value": "https://spark.lucko.me/0QhfjjtLHk"
    }
  },
  {
    "user": {
      "type": "player",
      "name": "Manzarli",
      "uniqueId": "741f774b-754a-49eb-93ac-fa7c0c120c28"
    },
    "time": 1751106513438,
    "type": "Profiler",
    "data": {
      "type": "url",
      "value": "https://spark.lucko.me/5T4JZIDpzv"
    }
  },
  {
    "user": {
      "type": "player",
      "name": "Manzarli",
      "uniqueId": "741f774b-754a-49eb-93ac-fa7c0c120c28"
    },
    "time": 1751106171317,
    "type": "Profiler",
    "data": {
      "type": "url",
      "value": "https://spark.lucko.me/M5HIxoSETh"
    }
  },
  {
    "user": {
      "type": "player",
      "name": "Manzarli",
      "uniqueId": "741f774b-754a-49eb-93ac-fa7c0c120c28"
    },
    "time": 1751105311587,
    "type": "Profiler",
    "data": {
      "type": "url",
      "value": "https://spark.lucko.me/Cyl0qLRJ68"
    }
  },
  {
    "user": {
      "type": "player",
      "name": "Manzarli",
      "uniqueId": "741f774b-754a-49eb-93ac-fa7c0c120c28"
    },
    "time": 1750614632336,
    "type": "Profiler",
    "data": {
      "type": "url",
      "value": "https://spark.lucko.me/fD7ffgr8Oq"
    }
  },
  {
    "user": {
      "type": "player",
      "name": "Manzarli",
      "uniqueId": "741f774b-754a-49eb-93ac-fa7c0c120c28"
    },
    "time": 1750424241324,
    "type": "Profiler",
    "data": {
      "type": "url",
      "value": "https://spark.lucko.me/KDKnPHVR9r"
    }
  },
  {
    "user": {
      "type": "player",
      "name": "Manzarli",
      "uniqueId": "741f774b-754a-49eb-93ac-fa7c0c120c28"
    },
    "time": 1750362387730,
    "type": "Profiler",
    "data": {
      "type": "url",
      "value": "https://spark.lucko.me/veZwwDhcsz"
    }
  },
  {
    "user": {
      "type": "player",
      "name": "Manzarli",
      "uniqueId": "741f774b-754a-49eb-93ac-fa7c0c120c28"
    },
    "time": 1750360609259,
    "type": "Profiler",
    "data": {
      "type": "url",
      "value": "https://spark.lucko.me/kJEESrKvzU"
    }
  },
  {
    "user": {
      "type": "player",
      "name": "Manzarli",
      "uniqueId": "741f774b-754a-49eb-93ac-fa7c0c120c28"
    },
    "time": 1750359224595,
    "type": "Profiler (live)",
    "data": {
      "type": "url",
      "value": "https://spark.lucko.me/wzY5Bo6fjg"
    }
  },
  {
    "user": {
      "type": "player",
      "name": "Manzarli",
      "uniqueId": "741f774b-754a-49eb-93ac-fa7c0c120c28"
    },
    "time": 1750357674857,
    "type": "Profiler",
    "data": {
      "type": "url",
      "value": "https://spark.lucko.me/i70Qs6vY22"
    }
  },
  {
    "user": {
      "type": "player",
      "name": "Manzarli",
      "uniqueId": "741f774b-754a-49eb-93ac-fa7c0c120c28"
    },
    "time": 1750356521664,
    "type": "Profiler",
    "data": {
      "type": "url",
      "value": "https://spark.lucko.me/yOsAVtygct"
    }
  },
  {
    "user": {
      "type": "player",
      "name": "Manzarli",
      "uniqueId": "741f774b-754a-49eb-93ac-fa7c0c120c28"
    },
    "time": 1750353725109,
    "type": "Profiler",
    "data": {
      "type": "url",
      "value": "https://spark.lucko.me/SAT3gqDv1K"
    }
  },
  {
    "user": {
      "type": "player",
      "name": "Manzarli",
      "uniqueId": "741f774b-754a-49eb-93ac-fa7c0c120c28"
    },
    "time": 1750352953939,
    "type": "Profiler (live)",
    "data": {
      "type": "url",
      "value": "https://spark.lucko.me/WHoRSeGqJJ"
    }
  },
  {
    "user": {
      "type": "player",
      "name": "Manzarli",
      "uniqueId": "741f774b-754a-49eb-93ac-fa7c0c120c28"
    },
    "time": 1750351821513,
    "type": "Profiler",
    "data": {
      "type": "url",
      "value": "https://spark.lucko.me/ixcTKGB4eE"
    }
  },
  {
    "user": {
      "type": "player",
      "name": "Manzarli",
      "uniqueId": "741f774b-754a-49eb-93ac-fa7c0c120c28"
    },
    "time": 1750350753981,
    "type": "Profiler",
    "data": {
      "type": "url",
      "value": "https://spark.lucko.me/zFk8zj7wGt"
    }
  }
]